hw_1/__init__.py
hw_1/build_ast.py
hse_python_hw_1_avushakova-0.0.5.dist-info/LICENSE
hse_python_hw_1_avushakova-0.0.5.dist-info/METADATA
hse_python_hw_1_avushakova-0.0.5.dist-info/WHEEL
hse_python_hw_1_avushakova-0.0.5.dist-info/top_level.txt
hse_python_hw_1_avushakova-0.0.5.dist-info/RECORD
