Metadata-Version: 2.1
Name: hse-python-hw-1-avushakova
Version: 0.0.5
Summary: A small example package
Home-page: https://github.com/AlinaUsh/HSE_Python
Author: Alina Ushakova
Author-email: spb.alina.ushakova@gmail.com
License: UNKNOWN
Project-URL: Bug Tracker, https://github.com/AlinaUsh/HSE_Python/issues
Platform: UNKNOWN
Classifier: Programming Language :: Python :: 3
Classifier: License :: OSI Approved :: MIT License
Classifier: Operating System :: OS Independent
Requires-Python: >=3.6
License-File: LICENSE
Requires-Dist: astunparse
Requires-Dist: networkx
Requires-Dist: matplotlib
Requires-Dist: pydot (>=1.2.4)
